hatch_protobuf/__init__.py
hatch_protobuf/_version.py
hatch_protobuf/hooks.py
hatch_protobuf/plugin.py
hatch_protobuf-0.5.0.dist-info/METADATA
hatch_protobuf-0.5.0.dist-info/WHEEL
hatch_protobuf-0.5.0.dist-info/entry_points.txt
hatch_protobuf-0.5.0.dist-info/licenses/LICENSE.md
hatch_protobuf-0.5.0.dist-info/RECORD
