Metadata-Version: 2.4
Name: hatch-protobuf
Version: 0.5.0
Summary: A Hatch build plugin to generate Python files from Protocol Buffers .proto files
Project-URL: Source code, https://github.com/nanoporetech/hatch-protobuf
Author-email: Oxford Nanopore Technologies PLC <info@nanoporetech.com>
License-Expression: MPL-2.0
License-File: LICENSE.md
Keywords: grpc,hatch,protobuf
Classifier: Development Status :: 2 - Pre-Alpha
Classifier: Framework :: Hatch
Classifier: Intended Audience :: Developers
Classifier: Programming Language :: Python
Classifier: Programming Language :: Python :: 3.9
Classifier: Programming Language :: Python :: 3.10
Classifier: Programming Language :: Python :: 3.11
Classifier: Programming Language :: Python :: 3.12
Classifier: Programming Language :: Python :: 3.13
Classifier: Programming Language :: Python :: Implementation :: CPython
Classifier: Topic :: Software Development :: Code Generators
Requires-Python: >=3.9
Requires-Dist: grpcio-tools~=1.49
Requires-Dist: hatchling
